xiao_asgi/__init__.py
xiao_asgi/applications.py
xiao_asgi/connections.py
xiao_asgi/requests.py
xiao_asgi/responses.py
xiao_asgi/routing.py
xiao_asgi-0.2.1.dist-info/LICENSE.txt
xiao_asgi-0.2.1.dist-info/WHEEL
xiao_asgi-0.2.1.dist-info/METADATA
xiao_asgi-0.2.1.dist-info/RECORD
