Metadata-Version: 2.1
Name: xiao-asgi
Version: 0.2.1
Summary: A small ASGI framework.
Home-page: https://github.com/limber-project/limberframework
License: MIT
Keywords: python,asgi
Author: Jonathan Staniforth
Author-email: jonathanstaniforth@gmail.com
Requires-Python: >=3.9,<4.0
Classifier: License :: OSI Approved :: MIT License
Classifier: Programming Language :: Python :: 3
Classifier: Programming Language :: Python :: 3.10
Classifier: Programming Language :: Python :: 3.9
Project-URL: Repository, https://github.com/limber-project/limberframework
